.DS_Store
textbag/preprocessing.py
textbag-1.1.4.dist-info/LICENSE.md
textbag-1.1.4.dist-info/METADATA
textbag-1.1.4.dist-info/WHEEL
textbag-1.1.4.dist-info/top_level.txt
textbag-1.1.4.dist-info/RECORD
