Metadata-Version: 2.1
Name: textbag
Version: 1.1.4
Summary: bag-of-words implementer and tools
Home-page: https://github.com/JacobDer/textbag
Author: Real Python
Author-email: jacobder9@gmail.com
License: MIT
Platform: UNKNOWN
Classifier: License :: OSI Approved :: MIT License
Classifier: Programming Language :: Python :: 3
Classifier: Programming Language :: Python :: 3.9
Requires-Dist: nltk
Requires-Dist: pandas
Requires-Dist: numpy
